x_4357_make_microservice_x/__init__.py
x_4357_make_microservice_x/__init__.pyi
x_4357_make_microservice_x/py.typed
x_4357_make_microservice_x/x_cls_make_microservice_artifact_publish_svc_x.py
x_4357_make_microservice_x/x_cls_make_microservice_artifact_publish_svc_x.pyi
x_4357_make_microservice_x-0.15.0.dist-info/METADATA
x_4357_make_microservice_x-0.15.0.dist-info/WHEEL
x_4357_make_microservice_x-0.15.0.dist-info/top_level.txt
x_4357_make_microservice_x-0.15.0.dist-info/RECORD
