Metadata-Version: 2.4
Name: x_4357_make_microservice_x
Version: 0.15.0
Summary: Makes microservices.
Author-email: "RRGM (Software Tech Lead of the Primus Pilus Night Watch AI Corporation)" <eye4357@outlook.com>
Requires-Python: >=3.8
